{
    "version": "0.2.0",
    "configurations": [
        {
            "name": "Python: docling RAG",
            "type": "python",
            "request": "launch",
            "program": "${workspaceFolder}/main.py",
            "console": "integratedTerminal",
            "args": [
                "--url", "content/DocLayNet.pdf",
                "--collection", "ai_research_papers",
                "--model", "BAAI/bge-small-en-v1.5",
                "--query", "What the six DocLayNet document categories used during training and their percentage?"
            ],
            "env": {
                "PYTHONPATH": "${workspaceFolder}"ß
            },
            "justMyCode": true
        }
    ]
}
